[
  {
    "type": "donation",
    "id": "2683e0b9-1fdd-4d78-b6e0-b9d5fbe5f0dc",
    "name": "Tolu Tolu",
    "avatarUrl": "https://platform-logos-myprofile-api-prod.s3.us-east-2.amazonaws.com/Tolufowobi.1779663925307",
    "category": "mentorship",
    "createdOn": "2026-05-24T23:06:37Z"
  },
  {
    "type": "donation",
    "id": "e70a0b13-3eca-4489-890d-24e4791899ce",
    "name": "Verachten Bruno",
    "avatarUrl": "https://platform-logos-myprofile-api-prod.s3.us-east-2.amazonaws.com/gounthar.1651215884869",
    "category": "mentorship",
    "createdOn": "2026-03-13T21:02:04Z"
  }
]